[
    {
        "provincia": "Álava",
        "idProvincia": "ES-VI",
        "idPais": "ES",
        "latitud": "42.85058789",
        "longitud": "-2.67275685",
        "idDelegacion": "4"
    },
    {
        "provincia": "Albacete",
        "idProvincia": "ES-AB",
        "idPais": "ES",
        "latitud": "38.99588053",
        "longitud": "-1.85574745",
        "idDelegacion": "9"
    },
    {
        "provincia": "Alicante",
        "idProvincia": "ES-A",
        "idPais": "ES",
        "latitud": "38.34548705",
        "longitud": "-0.4831832",
        "idDelegacion": "11"
    },
    {
        "provincia": "Almería",
        "idProvincia": "ES-AL",
        "idPais": "ES",
        "latitud": "36.83892362",
        "longitud": "-2.46413188",
        "idDelegacion": "14"
    },
    {
        "provincia": "Asturias",
        "idProvincia": "ES-O",
        "idPais": "ES",
        "latitud": "43.36232165",
        "longitud": "-5.84372206",
        "idDelegacion": "17"
    },
    {
        "provincia": "Aveiro",
        "idProvincia": "PT-AV",
        "idPais": "PT",
        "latitud": null,
        "longitud": null,
        "idDelegacion": "20"
    },
    {
        "provincia": "Ávila",
        "idProvincia": "ES-AV",
        "idPais": "ES",
        "latitud": "40.65586958",
        "longitud": "-4.69771277",
        "idDelegacion": "3"
    },
    {
        "provincia": "Badajoz",
        "idProvincia": "ES-BA",
        "idPais": "ES",
        "latitud": "38.87874339",
        "longitud": "-6.97099704",
        "idDelegacion": "13"
    },
    {
        "provincia": "Barcelona",
        "idProvincia": "ES-B",
        "idPais": "ES",
        "latitud": "41.38424664",
        "longitud": "2.17634927",
        "idDelegacion": "7"
    },
    {
        "provincia": "Beja",
        "idProvincia": "PT-BE",
        "idPais": "PT",
        "latitud": null,
        "longitud": null,
        "idDelegacion": "20"
    },
    {
        "provincia": "Braga",
        "idProvincia": "PT-BR",
        "idPais": "PT",
        "latitud": null,
        "longitud": null,
        "idDelegacion": "20"
    },
    {
        "provincia": "Braganza",
        "idProvincia": "PT-BA",
        "idPais": "PT",
        "latitud": null,
        "longitud": null,
        "idDelegacion": "20"
    },
    {
        "provincia": "Burgos",
        "idProvincia": "ES-BU",
        "idPais": "ES",
        "latitud": "42.34113004",
        "longitud": "-3.70419805",
        "idDelegacion": "3"
    },
    {
        "provincia": "Cáceres",
        "idProvincia": "ES-CC",
        "idPais": "ES",
        "latitud": "39.47316762",
        "longitud": "-6.37121092",
        "idDelegacion": "13"
    },
    {
        "provincia": "Cádiz",
        "idProvincia": "ES-CA",
        "idPais": "ES",
        "latitud": "36.52114",
        "longitud": "-6.28058",
        "idDelegacion": "14"
    },
    {
        "provincia": "Cantabria",
        "idProvincia": "ES-S",
        "idPais": "ES",
        "latitud": "43.46297885",
        "longitud": "-3.80474784",
        "idDelegacion": "4"
    },
    {
        "provincia": "Castellón",
        "idProvincia": "ES-CS",
        "idPais": "ES",
        "latitud": "39.98640809",
        "longitud": "-0.03688142",
        "idDelegacion": "9"
    },
    {
        "provincia": "Castelo Branco",
        "idProvincia": "PT-CB",
        "idPais": "PT",
        "latitud": null,
        "longitud": null,
        "idDelegacion": "20"
    },
    {
        "provincia": "Ceuta",
        "idProvincia": "ES-CE",
        "idPais": "ES",
        "latitud": "35.88810209",
        "longitud": "-5.30675127",
        "idDelegacion": "14"
    },
    {
        "provincia": "Ciudad Real",
        "idProvincia": "ES-CR",
        "idPais": "ES",
        "latitud": "38.98651781",
        "longitud": "-3.93131981",
        "idDelegacion": "2"
    },
    {
        "provincia": "Coímbra",
        "idProvincia": "PT-CO",
        "idPais": "PT",
        "latitud": null,
        "longitud": null,
        "idDelegacion": "20"
    },
    {
        "provincia": "Córdoba",
        "idProvincia": "ES-CO",
        "idPais": "ES",
        "latitud": "37.87954225",
        "longitud": "-4.78032455",
        "idDelegacion": "14"
    },
    {
        "provincia": "Cuenca",
        "idProvincia": "ES-CU",
        "idPais": "ES",
        "latitud": "40.07653762",
        "longitud": "-2.13152306",
        "idDelegacion": "2"
    },
    {
        "provincia": "Évora",
        "idProvincia": "PT-EV",
        "idPais": "PT",
        "latitud": null,
        "longitud": null,
        "idDelegacion": "20"
    },
    {
        "provincia": "Faro",
        "idProvincia": "PT-FA",
        "idPais": "PT",
        "latitud": null,
        "longitud": null,
        "idDelegacion": "20"
    },
    {
        "provincia": "Girona",
        "idProvincia": "ES-GI",
        "idPais": "ES",
        "latitud": "41.98186075",
        "longitud": "2.82411899",
        "idDelegacion": "7"
    },
    {
        "provincia": "Granada",
        "idProvincia": "ES-GR",
        "idPais": "ES",
        "latitud": "37.17641932",
        "longitud": "-3.60001883",
        "idDelegacion": "14"
    },
    {
        "provincia": "Guadalajara",
        "idProvincia": "ES-GU",
        "idPais": "ES",
        "latitud": "40.63435548",
        "longitud": "-3.16210273",
        "idDelegacion": "2"
    },
    {
        "provincia": "Guarda",
        "idProvincia": "PT-GU",
        "idPais": "PT",
        "latitud": null,
        "longitud": null,
        "idDelegacion": "20"
    },
    {
        "provincia": "Guipúzcoa",
        "idProvincia": "ES-SS",
        "idPais": "ES",
        "latitud": "43.31717158",
        "longitud": "-1.98191785",
        "idDelegacion": "4"
    },
    {
        "provincia": "Huelva",
        "idProvincia": "ES-H",
        "idPais": "ES",
        "latitud": "37.26004113",
        "longitud": "-6.95040588",
        "idDelegacion": "13"
    },
    {
        "provincia": "Huesca",
        "idProvincia": "ES-HU",
        "idPais": "ES",
        "latitud": "42.14062739",
        "longitud": "-0.40842276",
        "idDelegacion": "6"
    },
    {
        "provincia": "Islas Baleares",
        "idProvincia": "ES-PM",
        "idPais": "ES",
        "latitud": "39.57114699",
        "longitud": "2.65181698",
        "idDelegacion": "10"
    },
    {
        "provincia": "Jaén",
        "idProvincia": "ES-J",
        "idPais": "ES",
        "latitud": "37.7651913",
        "longitud": "-3.7903594",
        "idDelegacion": "14"
    },
    {
        "provincia": "La Coruña",
        "idProvincia": "ES-C",
        "idPais": "ES",
        "latitud": "43.37012643",
        "longitud": "-8.39114853",
        "idDelegacion": "18"
    },
    {
        "provincia": "La Rioja",
        "idProvincia": "ES-LO",
        "idPais": "ES",
        "latitud": "42.46644945",
        "longitud": "-2.44565538",
        "idDelegacion": "4"
    },
    {
        "provincia": "Las Palmas",
        "idProvincia": "ES-GC",
        "idPais": "ES",
        "latitud": "28.09937855",
        "longitud": "-15.41336841",
        "idDelegacion": "15"
    },
    {
        "provincia": "Leiría",
        "idProvincia": "PT-LE",
        "idPais": "PT",
        "latitud": null,
        "longitud": null,
        "idDelegacion": "20"
    },
    {
        "provincia": "León",
        "idProvincia": "ES-LE",
        "idPais": "ES",
        "latitud": "42.59912097",
        "longitud": "-5.56707631",
        "idDelegacion": "17"
    },
    {
        "provincia": "Lisboa",
        "idProvincia": "PT-LI",
        "idPais": "PT",
        "latitud": null,
        "longitud": null,
        "idDelegacion": "20"
    },
    {
        "provincia": "Lleida",
        "idProvincia": "ES-L",
        "idPais": "ES",
        "latitud": "41.61527355",
        "longitud": "0.62061934",
        "idDelegacion": "7"
    },
    {
        "provincia": "Lugo",
        "idProvincia": "ES-LU",
        "idPais": "ES",
        "latitud": "43.0091282",
        "longitud": "-7.55817392",
        "idDelegacion": "18"
    },
    {
        "provincia": "Madrid",
        "idProvincia": "ES-M",
        "idPais": "ES",
        "latitud": "40.40841191",
        "longitud": "-3.68760088",
        "idDelegacion": "2"
    },
    {
        "provincia": "Málaga",
        "idProvincia": "ES-MA",
        "idPais": "ES",
        "latitud": "36.72034267",
        "longitud": "-4.41997511",
        "idDelegacion": "14"
    },
    {
        "provincia": "Melilla",
        "idProvincia": "ES-ML",
        "idPais": "ES",
        "latitud": "35.294731",
        "longitud": "-2.942281",
        "idDelegacion": "14"
    },
    {
        "provincia": "Murcia",
        "idProvincia": "ES-MU",
        "idPais": "ES",
        "latitud": "37.98436361",
        "longitud": "-1.1285408",
        "idDelegacion": "11"
    },
    {
        "provincia": "Navarra",
        "idProvincia": "ES-NA",
        "idPais": "ES",
        "latitud": "42.814102",
        "longitud": "-1.6451528",
        "idDelegacion": "6"
    },
    {
        "provincia": "Oporto",
        "idProvincia": "PT-PO",
        "idPais": "PT",
        "latitud": null,
        "longitud": null,
        "idDelegacion": "20"
    },
    {
        "provincia": "Orense",
        "idProvincia": "ES-OR",
        "idPais": "ES",
        "latitud": "42.33654919",
        "longitud": "-7.86368375",
        "idDelegacion": "18"
    },
    {
        "provincia": "Palencia",
        "idProvincia": "ES-P",
        "idPais": "ES",
        "latitud": "42.0078373",
        "longitud": "-4.53460106",
        "idDelegacion": "3"
    },
    {
        "provincia": "Pontevedra",
        "idProvincia": "ES-PO",
        "idPais": "ES",
        "latitud": "42.43381442",
        "longitud": "-8.64799018",
        "idDelegacion": "18"
    },
    {
        "provincia": "Portalegre",
        "idProvincia": "PT-PA",
        "idPais": "PT",
        "latitud": null,
        "longitud": null,
        "idDelegacion": "20"
    },
    {
        "provincia": "Salamanca",
        "idProvincia": "ES-SA",
        "idPais": "ES",
        "latitud": "40.96736822",
        "longitud": "-5.66538084",
        "idDelegacion": "3"
    },
    {
        "provincia": "Santarém",
        "idProvincia": "PT-SA",
        "idPais": "PT",
        "latitud": null,
        "longitud": null,
        "idDelegacion": "20"
    },
    {
        "provincia": "Segovia",
        "idProvincia": "ES-SG",
        "idPais": "ES",
        "latitud": "40.9498703",
        "longitud": "-4.12524116",
        "idDelegacion": "3"
    },
    {
        "provincia": "Setúbal",
        "idProvincia": "PT-SE",
        "idPais": "PT",
        "latitud": null,
        "longitud": null,
        "idDelegacion": "20"
    },
    {
        "provincia": "Sevilla",
        "idProvincia": "ES-SE",
        "idPais": "ES",
        "latitud": "37.38620512",
        "longitud": "-5.99251368",
        "idDelegacion": "13"
    },
    {
        "provincia": "Soria",
        "idProvincia": "ES-SO",
        "idPais": "ES",
        "latitud": "41.76327912",
        "longitud": "-2.46624798",
        "idDelegacion": "6"
    },
    {
        "provincia": "Tarragona",
        "idProvincia": "ES-T",
        "idPais": "ES",
        "latitud": "41.11910287",
        "longitud": "1.2584219",
        "idDelegacion": "7"
    },
    {
        "provincia": "Tenerife",
        "idProvincia": "ES-TF",
        "idPais": "ES",
        "latitud": "28.46285408",
        "longitud": "-16.24720629",
        "idDelegacion": "15"
    },
    {
        "provincia": "Teruel",
        "idProvincia": "ES-TE",
        "idPais": "ES",
        "latitud": "40.34412951",
        "longitud": "-1.10927177",
        "idDelegacion": "6"
    },
    {
        "provincia": "Toledo",
        "idProvincia": "ES-TO",
        "idPais": "ES",
        "latitud": "39.85715187",
        "longitud": "-4.02431421",
        "idDelegacion": "2"
    },
    {
        "provincia": "Valencia",
        "idProvincia": "ES-V",
        "idPais": "ES",
        "latitud": "39.47534441",
        "longitud": "-0.37565717",
        "idDelegacion": "9"
    },
    {
        "provincia": "Valladolid",
        "idProvincia": "ES-VA",
        "idPais": "ES",
        "latitud": "41.65232777",
        "longitud": "-4.72334924",
        "idDelegacion": "3"
    },
    {
        "provincia": "Viana do Castelo",
        "idProvincia": "PT-VC",
        "idPais": "PT",
        "latitud": null,
        "longitud": null,
        "idDelegacion": "20"
    },
    {
        "provincia": "Vila Real",
        "idProvincia": "PT-VR",
        "idPais": "PT",
        "latitud": null,
        "longitud": null,
        "idDelegacion": "20"
    },
    {
        "provincia": "Viseu",
        "idProvincia": "PT-VI",
        "idPais": "PT",
        "latitud": null,
        "longitud": null,
        "idDelegacion": "20"
    },
    {
        "provincia": "Vizcaya",
        "idProvincia": "ES-BI",
        "idPais": "ES",
        "latitud": "43.25721957",
        "longitud": "-2.92390606",
        "idDelegacion": "4"
    },
    {
        "provincia": "Zamora",
        "idProvincia": "ES-ZA",
        "idPais": "ES",
        "latitud": "41.49913956",
        "longitud": "-5.75494831",
        "idDelegacion": "3"
    },
    {
        "provincia": "Zaragoza",
        "idProvincia": "ES-Z",
        "idPais": "ES",
        "latitud": "41.65645655",
        "longitud": "-0.87928652",
        "idDelegacion": "6"
    }
]
